LICENSE
README.md
flask_tunnel.py
setup.py
flask_tunnel.egg-info/PKG-INFO
flask_tunnel.egg-info/SOURCES.txt
flask_tunnel.egg-info/dependency_links.txt
flask_tunnel.egg-info/requires.txt
flask_tunnel.egg-info/top_level.txt