Metadata-Version: 2.1
Name: flask-tunnel
Version: 0.1.5
Summary: Configurable ngrok tunneling for Flask apps.
Home-page: https://github.com/Wolfiej-k/flask-tunnel
Author: Taj Jethwani-Keyser
License: MIT
Classifier: Programming Language :: Python :: 3.9
Classifier: License :: OSI Approved :: MIT License
License-File: LICENSE
